pyRDDLGym_symbolic/__init__.py
pyRDDLGym_symbolic/core/__init__.py
pyRDDLGym_symbolic/core/levels.py
pyRDDLGym_symbolic/core/model.py
pyRDDLGym_symbolic/core/simulator.py
pyRDDLGym_symbolic/core/visualizer.py
pyRDDLGym_symbolic/examples/__init__.py
pyRDDLGym_symbolic/examples/run_dbn_visualization.py
pyRDDLGym_symbolic/examples/run_pe.py
pyRDDLGym_symbolic/examples/run_simulation.py
pyRDDLGym_symbolic/examples/run_vi.py
pyRDDLGym_symbolic/examples/run_xadd_compilation.py
pyRDDLGym_symbolic/mdp/__init__.py
pyRDDLGym_symbolic/mdp/action.py
pyRDDLGym_symbolic/mdp/mdp.py
pyRDDLGym_symbolic/mdp/mdp_parser.py
pyRDDLGym_symbolic/mdp/policy.py
pyRDDLGym_symbolic/mdp/policy_parser.py
pyRDDLGym_symbolic/solver/__init__.py
pyRDDLGym_symbolic/solver/base.py
pyRDDLGym_symbolic/solver/pe.py
pyRDDLGym_symbolic/solver/vi.py
pyRDDLGym_symbolic/utils/__init__.py
pyRDDLGym_symbolic/utils/xadd_utils.py
pyRDDLGym_symbolic-0.0.11.dist-info/LICENSE
pyRDDLGym_symbolic-0.0.11.dist-info/METADATA
pyRDDLGym_symbolic-0.0.11.dist-info/WHEEL
pyRDDLGym_symbolic-0.0.11.dist-info/top_level.txt
pyRDDLGym_symbolic-0.0.11.dist-info/RECORD
