Metadata-Version: 2.1
Name: pyRDDLGym_symbolic
Version: 0.0.11
Summary: pyRDDLGym-symbolic: Symbolic toolset for pyRDDLGym via XADD.
Home-page: https://github.com/pyrddlgym-project/pyRDDLGym-symbolic
Author: Jihwan Jeong, Michael Gimelfarb, Scott Sanner
Author-email: Jihwan Jeong <jiihwan.jeong@gmail.com>
License: MIT License
Project-URL: Homepage, https://github.com/jihwan-jeong/xaddpy
Project-URL: Bug Tracker, https://github.com/jihwan-jeong/xaddpy/issues
Keywords: pyRDDLGym,Symbolic Dynamic Programming,RDDL,Dynamic Bayes Net
Classifier: Development Status :: 3 - Alpha
Classifier: Intended Audience :: Science/Research
Classifier: License :: OSI Approved :: MIT License
Classifier: Natural Language :: English
Classifier: Operating System :: OS Independent
Classifier: Programming Language :: Python :: 3
Classifier: Topic :: Scientific/Engineering :: Artificial Intelligence
Requires-Python: >=3.8
License-File: LICENSE
Requires-Dist: symengine >=0.11.0
Requires-Dist: pyRDDLGym >=2.0
Requires-Dist: xaddpy >=0.2.8
Requires-Dist: sympy >=1.12
